{"city":"Tottori","user_id":62521661,"xl_picture_url":"https://a2.muscache.com/im/pictures/ea8a17f6-f176-427f-b96c-82460ddd4fc7.jpg?aki_policy=x_large","lat":35.521600292442365,"lng":133.97292771108204,"country":"Japan","name":"1min to the beach. Tatami room.","instant_bookable":false,"bathrooms":1,"bedrooms":1,"beds":8,"min_nights":1,"neighborhood":null,"person_capacity":8,"state":"Tottori Prefecture","zipcode":"689-0501","address":"nagawase aoya-cho, Tottori, Tottori Prefecture 689-0501, Japan","country_code":"JP","cancellation_policy":"strict","property_type":"House","reviews_count":1,"room_type":"Private room","room_type_category":"private_room","bed_type":"Real Bed","bed_type_category":"real_bed","check_in_time":null,"check_in_time_ends_at":null,"check_out_time":null,"guests_included":3,"max_nights":1125,"locale":"ja","localized_city":"Tottori","language":"ja","experiences_offered":"none","max_nights_input_value":1125,"min_nights_input_value":1,"property_type_id":2,"cleaning_fee_native":10,"extras_price_native":10,"description_locale":"ja","space":"この家には､私の両親と祖父の3人が住んでいます｡泊まっていただくｽﾍﾟｰｽは個室ですが､ｷｯﾁﾝ､ﾄｲﾚ､浴室などは家族との共有となります｡今まで､何人もの交換留学生を受け入れてきてきました｡ﾊﾞｰﾍﾞｷｭｰをしてみたい､山を探検してみたい､畑仕事をしてみたい､釣りに行きたいなどﾘｸｴｽﾄがありましたらお気軽にご相談ください!\n\nMy pearents and grandfather are living at this house. Please share with host family if you use kitchen, bathroom, toilet.  If you want to go to fishing, barbeque or to hike at mountain please request to us!","access":"個室､ﾄｲﾚ､浴室､はご自由にどうぞ｡ｷｯﾁﾝ､洗濯機については使用している事もありますので､時間などお気軽にご相談ください｡\n\nif you want to use kitchen and washing machine, please ask  host family. ","amenities":["TV","Wireless Internet","Air Conditioning","Kitchen","Free Parking on Premises","Hot Tub","Heating","Family/Kid Friendly","Washer","Dryer","Smoke Detector","First Aid Kit","Fire Extinguisher","Essentials","Shampoo"],"in_building":false,"in_landlord_partnership":false,"in_toto_area":false,"calendar_updated_at":"today","price_for_extra_person_native":20,"time_zone_name":"Asia/Tokyo","smart_pricing_available":true,"guest_controls":{"allows_children_as_host":true,"allows_infants_as_host":true,"allows_pets_as_host":false,"allows_smoking_as_host":false,"allows_events_as_host":false,"id":13031620},"check_in_time_start":"NOT_SELECTED","check_in_time_end":"NOT_SELECTED","formatted_check_out_time":"NOT_SELECTED"}